main.py
jinja2_max-0.1.1.dist-info/METADATA
jinja2_max-0.1.1.dist-info/WHEEL
jinja2_max-0.1.1.dist-info/entry_points.txt
jinja2_max-0.1.1.dist-info/top_level.txt
jinja2_max-0.1.1.dist-info/RECORD
